crtstream/__init__.py
crtstream/cli.py
crtstream/data/logs.json
crtstream-0.1.5.dist-info/licenses/LICENSE
crtstream-0.1.5.dist-info/METADATA
crtstream-0.1.5.dist-info/WHEEL
crtstream-0.1.5.dist-info/entry_points.txt
crtstream-0.1.5.dist-info/top_level.txt
crtstream-0.1.5.dist-info/RECORD
