Metadata-Version: 2.4
Name: crtstream
Version: 0.1.5
Summary: Certificate Transparency log streamer
Author-email: Your Name <you@example.com>
License: MIT
Requires-Python: >=3.9
License-File: LICENSE
Requires-Dist: requests>=2.28
Requires-Dist: cryptography>=41
Requires-Dist: python-dotenv>=1.0
Dynamic: license-file
